h2client/__init__.py
h2client/connection.py
h2client/diskcached_connection.py
h2client/http2_connection.py
h2client/request_connection.py
h2client/session.py
h2client/simple_connection.py
h2client/stream_connection.py
h2client-0.2.3.dist-info/LICENSE.txt
h2client-0.2.3.dist-info/METADATA
h2client-0.2.3.dist-info/WHEEL
h2client-0.2.3.dist-info/top_level.txt
h2client-0.2.3.dist-info/RECORD
