Metadata-Version: 2.1
Name: h2client
Version: 0.2.3
Summary: A connection-aware, cache-control respecting http/2 over tls client
Home-page: https://github.com/tjstretchalot/h2client
Author: Timothy Moore
Author-email: mtimothy984@gmail.com
License: UNKNOWN
Platform: UNKNOWN
Classifier: Programming Language :: Python :: 3
Classifier: Programming Language :: Python :: 3.8
Classifier: License :: CC0 1.0 Universal (CC0 1.0) Public Domain Dedication
Classifier: Topic :: Internet :: WWW/HTTP
Classifier: Topic :: Software Development :: Libraries :: Python Modules
License-File: LICENSE.txt
Requires-Dist: h2
Requires-Dist: httpx
Requires-Dist: diskcache
